ptock/__init__.py
ptock/font.py
ptock/main.py
ptock/mechanism.py
ptock/view.py
python3_ptock-1.3.1.dist-info/LICENSE
python3_ptock-1.3.1.dist-info/METADATA
python3_ptock-1.3.1.dist-info/WHEEL
python3_ptock-1.3.1.dist-info/entry_points.txt
python3_ptock-1.3.1.dist-info/top_level.txt
python3_ptock-1.3.1.dist-info/RECORD
