Metadata-Version: 2.1
Name: python3-ptock
Version: 1.3.1
Summary: A digital clock made in Python for the terminal, inspired by tty-clock and tock.
Author-email: Andre Ribeiro <andre.ribeiro.srs@gmail.com>
License: MIT
Project-URL: Homepage, https://github.com/andrerclaudio/python3-ptock
Project-URL: Issues, https://github.com/andrerclaudio/python3-ptock/issues
Keywords: digital clock,terminal,tty-clock,tock
Classifier: Programming Language :: Python :: 3
Classifier: License :: OSI Approved :: MIT License
Classifier: Operating System :: OS Independent
Requires-Python: >=3.12.7
License-File: LICENSE
